README.md
setup.py
power_nlp/__init__.py
power_nlp/power.py
power_nlp.egg-info/PKG-INFO
power_nlp.egg-info/SOURCES.txt
power_nlp.egg-info/dependency_links.txt
power_nlp.egg-info/top_level.txt