Metadata-Version: 2.1
Name: power-nlp
Version: 1.0
Summary: power nlp
Home-page: https://github.com/ExpertOfAI/power_nlp
Author: ExpertOfAI
License: MIT
Classifier: Programming Language :: Python :: 3
Classifier: License :: OSI Approved :: MIT License
Classifier: Operating System :: OS Independent
Requires-Python: >=3.6
